torchdrift/__init__.py
torchdrift/data/__init__.py
torchdrift/data/functional/__init__.py
torchdrift/data/functional/corruption_functions.py
torchdrift/detectors/__init__.py
torchdrift/detectors/detector.py
torchdrift/detectors/ks.py
torchdrift/detectors/mmd.py
torchdrift/reducers/__init__.py
torchdrift/reducers/pca.py
torchdrift/reducers/reducer.py
torchdrift/utils/__init__.py
torchdrift/utils/experiments.py
torchdrift/utils/fit.py
torchdrift-0.1.0.post1.dist-info/LICENSE
torchdrift-0.1.0.post1.dist-info/METADATA
torchdrift-0.1.0.post1.dist-info/WHEEL
torchdrift-0.1.0.post1.dist-info/top_level.txt
torchdrift-0.1.0.post1.dist-info/RECORD
