Metadata-Version: 2.1
Name: torchdrift
Version: 0.1.0.post1
Summary: Drift Detection for PyTorch
Home-page: https://torchdrift.org/
Author: Orobix Srl and MathInf GmbH
License: UNKNOWN
Platform: UNKNOWN
Requires-Dist: torch
